sallyjr/__init__.py
sallyjr/sallyjr.py
sallyjr-0.1.0.dist-info/METADATA
sallyjr-0.1.0.dist-info/WHEEL
sallyjr-0.1.0.dist-info/entry_points.txt
sallyjr-0.1.0.dist-info/RECORD
