Metadata-Version: 2.1
Name: sallyjr
Version: 0.1.0
Summary: Python client for the Sally Jr API
License: MIT
Author: Michael Daigler
Author-email: michael@conncreekroad.com
Requires-Python: >=3.10,<4.0
Classifier: License :: OSI Approved :: MIT License
Classifier: Programming Language :: Python :: 3
Classifier: Programming Language :: Python :: 3.10
Classifier: Programming Language :: Python :: 3.11
Requires-Dist: requests (>=2.25.1,<3.0.0)
